emailtoolkit/__init__.py
emailtoolkit/__init__.pyi
emailtoolkit/_version.py
emailtoolkit/emails.py
emailtoolkit/main.py
emailtoolkit/models.py
emailtoolkit/py.typed
emailtoolkit/configs/config.example.json
emailtoolkit/utils/__init__.py
emailtoolkit/utils/cache.py
emailtoolkit/utils/config.py
emailtoolkit/utils/disposable.py
emailtoolkit/utils/dns.py
emailtoolkit/utils/encoding.py
emailtoolkit/utils/logger.py
emailtoolkit/utils/smtp_probe.py
emailtoolkit-0.1.4.dist-info/METADATA
emailtoolkit-0.1.4.dist-info/WHEEL
emailtoolkit-0.1.4.dist-info/entry_points.txt
emailtoolkit-0.1.4.dist-info/licenses/LICENSE
emailtoolkit-0.1.4.dist-info/RECORD
