Metadata-Version: 2.4
Name: emailtoolkit
Version: 0.1.4
Summary: RFC-aware email parsing, normalization, extraction, and DNS health checks with env-config and a phonenumbers-like API.
Project-URL: Homepage, https://github.com/imyourboyroy/emailtoolkit
Project-URL: Repository, https://github.com/imyourboyroy/emailtoolkit
Project-URL: Bug Tracker, https://github.com/imyourboyroy/emailtoolkit/issues
Author-email: ItsYourBoyRoy <roy.dawson.iv@gmail.com>
License: MIT
License-File: LICENSE
Keywords: dns,email,email-validator,idna,normalizer,parser,rfc,validation
Classifier: Development Status :: 4 - Beta
Classifier: License :: OSI Approved :: MIT License
Classifier: Operating System :: OS Independent
Classifier: Programming Language :: Python :: 3
Classifier: Programming Language :: Python :: 3.9
Classifier: Programming Language :: Python :: 3.10
Classifier: Programming Language :: Python :: 3.11
Classifier: Programming Language :: Python :: 3.12
Classifier: Programming Language :: Python :: 3.13
Classifier: Topic :: Communications :: Email
Classifier: Topic :: Software Development :: Libraries :: Python Modules
Classifier: Typing :: Typed
Requires-Python: >=3.9
Requires-Dist: email-validator>=2.2.0
Requires-Dist: idna>=3.10
Provides-Extra: dns
Requires-Dist: dnspython>=2.7.0; extra == 'dns'
Provides-Extra: dotenv
Requires-Dist: python-dotenv>=1.1.1; extra == 'dotenv'
